README.md
setup.cfg
setup.py
optix/ABCDformalism.py
optix/__init__.py
optix/beams.py
optix/helper.py
optix.egg-info/PKG-INFO
optix.egg-info/SOURCES.txt
optix.egg-info/dependency_links.txt
optix.egg-info/requires.txt
optix.egg-info/top_level.txt